[
  {
    "Author": "Ninethirty77",
    "Name": "The Studium",
    "InternalName": "FCMetrics",
    "AssemblyVersion": "0.1.214.0",
    "Description": "The Studium app is an essential companion app for all Studium Members.",
    "Changelog": "GreenZone standings layout:\n- Fine-tunes the expanded weekly standings row spacing for the fourth entry.\n- Slightly reduces the main GreenZone window height after the standings expansion.",
    "ApplicableVersion": "any",
    "Tags": [
      "free company",
      "fc",
      "metrics",
      "graph",
      "crafting"
    ],
    "DalamudApiLevel": 15,
    "LoadRequiredState": 0,
    "LoadSync": false,
    "CanUnloadAsync": false,
    "LoadPriority": 0,
    "IconUrl": "https://raw.githubusercontent.com/Ninethirty77/the-greenzone-repo/main/icon.jpg",
    "Punchline": "An essential companion app for all Studium members.",
    "AcceptsFeedback": true,
    "IsHide": false,
    "IsTestingExclusive": false,
    "DownloadLinkInstall": "https://raw.githubusercontent.com/Ninethirty77/the-greenzone-repo/main/latest.zip",
    "DownloadLinkUpdate": "https://raw.githubusercontent.com/Ninethirty77/the-greenzone-repo/main/latest.zip",
    "RepoUrl": "https://github.com/Ninethirty77/the-greenzone-repo",
    "LastUpdate": "1783989601"
  }
]
